odoo/addons/account_set_reconcilable/README.rst
odoo/addons/account_set_reconcilable/__init__.py
odoo/addons/account_set_reconcilable/__manifest__.py
odoo/addons/account_set_reconcilable/i18n/account_set_reconcilable.pot
odoo/addons/account_set_reconcilable/models/__init__.py
odoo/addons/account_set_reconcilable/models/account_account.py
odoo/addons/account_set_reconcilable/readme/CONTRIBUTORS.rst
odoo/addons/account_set_reconcilable/readme/DESCRIPTION.rst
odoo/addons/account_set_reconcilable/static/description/icon.png
odoo/addons/account_set_reconcilable/static/description/index.html
odoo/addons/account_set_reconcilable/tests/__init__.py
odoo/addons/account_set_reconcilable/tests/test_account_set_reconcilable.py
odoo11_addon_account_set_reconcilable-11.0.1.0.0.99.dev7.dist-info/METADATA
odoo11_addon_account_set_reconcilable-11.0.1.0.0.99.dev7.dist-info/WHEEL
odoo11_addon_account_set_reconcilable-11.0.1.0.0.99.dev7.dist-info/top_level.txt
odoo11_addon_account_set_reconcilable-11.0.1.0.0.99.dev7.dist-info/RECORD
